[{
  "name": "Salsa de tomate clásica",
  "description": "La salsa de tomate es una de las opciones más tradicionales y populares para una pizza.",
  "available": true
},{
  "name": "Salsa de tomate con hierbas",
  "description": "Salsa de tomate con hierbas frescas como albahaca, orégano y tomillo para darle un sabor más aromático y delicioso.",
  "available": true
},{
  "name": "Salsa de tomate con ajo",
  "description": "Una variante de la salsa de tomate clásica, pero con un toque de ajo picado para agregar sabor y aroma.",
  "available": true
},{
  "name": "Salsa de pesto",
  "description": "El pesto es una mezcla de albahaca fresca, piñones, ajo, queso parmesano y aceite de oliva. Es una opción deliciosa y aromática para una pizza.",
  "available": true
},{
  "name": "Salsa de barbacoa",
  "description": "Salsa de barbacoa para una pizza con sabores ahumados y dulces.",
  "available": true
},{
  "name": "Salsa de buffalo",
  "description": "Salsa de buffalo hecha con salsa de pimienta de cayena y mantequilla, para un sabor picante y un poco picante.",
  "available": true
},{
  "name": "Salsa de tomate con vino tinto",
  "description": "Variante más sofisticada de la salsa de tomate tradicional, que incluye vino tinto para darle un toque de sabor adicional.",
  "available": true
}]